foodunits/__init__.py
foodunits/base.py
foodunits/convertor.py
foodunits/exceptions.py
foodunits/utils/__init__.py
foodunits/utils/units.py
foodunits/utils/utils.py
foodunits/validator.py
foodunits-0.1.0.dist-info/LICENSE
foodunits-0.1.0.dist-info/WHEEL
foodunits-0.1.0.dist-info/METADATA
foodunits-0.1.0.dist-info/RECORD
