Metadata-Version: 2.1
Name: foodunits
Version: 0.1.0
Summary: Validate or convert food units
License: MIT
Author: Ben Zhang
Requires-Python: >=3.9
Classifier: License :: OSI Approved :: MIT License
Classifier: Programming Language :: Python :: 3
Classifier: Programming Language :: Python :: 3.9
Requires-Dist: Pattern (>=3.6)
Requires-Dist: fuzzywuzzy (>=0.18.0)
Requires-Dist: pycountry (>=22.3.5)
